Metadata-Version: 2.1
Name: mcdm
Version: 1.4
Summary: Python implementation of multiple-criteria decision-making algorithms
Home-page: https://github.com/akestoridis/mcdm
Author: Dimitrios-Georgios Akestoridis
Author-email: akestoridis@gmail.com
License: MIT
Keywords: multiple-criteria decision-making,evaluation,ranking,scoring,weighting,correlation,normalization
Classifier: Intended Audience :: Science/Research
Classifier: License :: OSI Approved :: MIT License
Classifier: Operating System :: MacOS
Classifier: Operating System :: Microsoft :: Windows
Classifier: Operating System :: POSIX :: Linux
Classifier: Programming Language :: Python :: 3.7
Classifier: Programming Language :: Python :: 3.8
Classifier: Programming Language :: Python :: 3.9
Classifier: Programming Language :: Python :: 3.10
Requires-Python: >=3.7, <4
License-File: LICENSE.txt
Requires-Dist: numpy (<2,>=1.21.6)
